setuptools_changelog/__init__.py
setuptools_changelog/changelog.py
setuptools_changelog-1.0.0.dist-info/METADATA
setuptools_changelog-1.0.0.dist-info/RECORD
setuptools_changelog-1.0.0.dist-info/WHEEL
setuptools_changelog-1.0.0.dist-info/entry_points.txt
setuptools_changelog-1.0.0.dist-info/top_level.txt
