Metadata-Version: 2.1
Name: setuptools-changelog
Version: 1.0.0
Summary: Setuptools extension to help generate change logs
Home-page: https://github.com/kxepal/setuptools-changelog
Author: Alexander Shorin
Author-email: kxepal@gmail.com
License: Apache 2.0
Keywords: setuptools,build,changelog
Platform: UNKNOWN
Classifier: Development Status :: 3 - Alpha
Classifier: Intended Audience :: Developers
Classifier: License :: OSI Approved :: Apache Software License
Classifier: Programming Language :: Python :: 2.7
Classifier: Programming Language :: Python :: 3.5
Classifier: Programming Language :: Python :: 3.6
Classifier: Topic :: Software Development :: Libraries
Requires-Python: >=2.7, !=3.0.*, !=3.1.*, !=3.2.*, !=3.3.*
Provides-Extra: develop
Requires-Dist: semver
Provides-Extra: develop
Requires-Dist: autoflake (==1.2); extra == 'develop'
Requires-Dist: mock (==2.0.0); extra == 'develop'
Requires-Dist: pyflakes (==1.6.0); extra == 'develop'
Requires-Dist: pytest-cov (==2.5.1); extra == 'develop'
Requires-Dist: pytest-flake8 (==1.0.1); extra == 'develop'
Requires-Dist: pytest-isort (==0.2.0); extra == 'develop'
Requires-Dist: pytest-pylint (==0.9.0); extra == 'develop'
Requires-Dist: pytest-runner; extra == 'develop'
Requires-Dist: pytest-sugar (==0.9.1); extra == 'develop'
Requires-Dist: pytest (==3.5.1); extra == 'develop'
